{
  "metadata": {
    "dataset": "cifar100",
    "data_root": "data",
    "model": "resnet50",
    "keep_ratio": 40,
    "selection_method": "learned_group",
    "seed": 22,
    "epochs": 200,
    "batch_size": 128,
    "optimizer": "SGD",
    "momentum": 0.9,
    "weight_decay": 0.0005,
    "init_lr": 0.1,
    "lr_schedule": {
      "type": "MultiStepLR",
      "milestones": [
        60,
        120,
        160
      ],
      "gamma": 0.2
    },
    "num_selected": 20000,
    "num_total": 50000
  },
  "accuracy": 0.6573,
  "accuracy_samples": [
    0.6559,
    0.657,
    0.6576,
    0.6571,
    0.658,
    0.6571,
    0.6572,
    0.6565,
    0.6593,
    0.6575
  ],
  "time_seconds": 1751.981094121933
}