{
  "metadata": {
    "dataset": "tiny-imagenet",
    "data_root": "data",
    "model": "resnet50",
    "keep_ratio": 40,
    "selection_method": "random",
    "seed": 22,
    "epochs": 90,
    "batch_size": 64,
    "physical_batch_size": 64,
    "grad_accum_steps": 4,
    "effective_batch_size": 256,
    "reference_effective_batch_size": 256,
    "optimizer": "SGD",
    "momentum": 0.9,
    "weight_decay": 0.0001,
    "init_lr": 0.1,
    "use_amp": true,
    "lr_schedule": {
      "type": "MultiStepLR",
      "milestones": [
        30,
        60
      ],
      "gamma": 0.1
    },
    "num_selected": 40000,
    "num_total": 100000
  },
  "accuracy": 0.4846,
  "accuracy_samples": [
    0.4836,
    0.4836,
    0.487,
    0.4826,
    0.4873,
    0.4849,
    0.4844,
    0.484,
    0.4849,
    0.4835
  ],
  "time_seconds": 3266.5126135349274
}